[
  {
    "name": "神户华侨同仁会病院",
    "jpName": "神戸華僑同仁会病院",
    "region": "神户",
    "address": "兵库县神户市中央区",
    "addressShort": "兵库县 神户市中央区",
    "phone": "078-222-XXXX",
    "langs": [
      "中文",
      "英文"
    ],
    "langDetail": "中文（全科）",
    "depts": [
      "内科",
      "外科",
      "产科",
      "儿科",
      "骨科",
      "眼科"
    ],
    "hours": "周一至周五 9:00–17:30 / 周六 9:00–12:30",
    "hoursShort": "周一至周五 9:00–17:30",
    "closed": "周日・节假日",
    "note": "全科均设中文医生或中文翻译，无需另行预约翻译服务。为关西地区历史最悠久的华人医院。",
    "updated": "2025-12",
    "searchKeys": "神户华侨同仁会病院"
  },
  {
    "name": "聖路加国際病院",
    "jpName": "St. Luke's International Hospital",
    "region": "东京",
    "address": "东京都中央区明石町9-1",
    "addressShort": "东京都 中央区 明石町（築地駅 徒步7分）",
    "phone": "预约中心: 03-5550-7120",
    "langs": [
      "中文",
      "英文"
    ],
    "langDetail": "中文 英文 韩文 俄文",
    "depts": [
      "内科",
      "外科",
      "产科",
      "妇科",
      "儿科",
      "肿瘤科",
      "急诊"
    ],
    "hours": "平日 8:30–（各科不同）",
    "warning": "需持紹介状预约，无紹介状不受诊",
    "closed": "第2土曜・周日・节假日",
    "note": "东京都指定外国人患者拠点医疗机构，中文通译员常驻，官网有完整中文版。需持紹介状及提前预约，无紹介状不受诊。築地駅步行7分。",
    "updated": "2026-04",
    "extraBadges": [
      {
        "label": "拠点病院",
        "type": "new"
      }
    ],
    "searchKeys": "聖路加国際病院 东京"
  },
  {
    "name": "順天堂医院 国際診療部",
    "jpName": "順天堂大学医学部附属順天堂医院",
    "region": "东京",
    "address": "东京都文京区本郷3-1-3",
    "addressShort": "东京都 文京区 本郷（御茶ノ水駅 徒步5分）",
    "phone": "03-5802-1985（国際診療部）",
    "langs": [
      "中文",
      "英文"
    ],
    "langDetail": "中文 英文",
    "depts": [
      "内科",
      "外科",
      "神经科",
      "心脏科",
      "肿瘤科",
      "产科",
      "整形外科"
    ],
    "hours": "平日 9:00–（各科不同）",
    "warning": "需紹介状＋医疗通译同行",
    "closed": "第2土曜・周日・节假日",
    "note": "东京都指定外国人患者拠点医疗机构，官网有中文版。在日外国人须自带医疗通译同行，无通译当日不受诊。需紹介状。御茶ノ水駅步行5分。",
    "updated": "2026-04",
    "extraBadges": [
      {
        "label": "拠点病院",
        "type": "new"
      }
    ],
    "searchKeys": "順天堂医院 国際診療部 东京"
  },
  {
    "name": "東京科学大学病院 国際医療部",
    "jpName": "東京科学大学病院（旧・東京医科歯科大学病院）",
    "region": "东京",
    "address": "东京都文京区湯島1-5-45",
    "addressShort": "东京都 文京区 湯島（御茶ノ水駅 徒步3分）",
    "phone": "03-5803-5650（国際医療部）",
    "langs": [
      "中文",
      "英文"
    ],
    "langDetail": "中文 英文 及19语言通译平板",
    "depts": [
      "内科",
      "外科",
      "牙科",
      "儿科",
      "产科",
      "眼科",
      "耳鼻喉科",
      "皮肤科"
    ],
    "hours": "平日 8:30–17:00（各科不同）",
    "warning": "需持紹介状预约",
    "closed": "周六・周日・节假日",
    "note": "旧东京医科歯科大学医院，国際医療部中英文员工常驻，提供19语言通译平板（免费）。官网有中文版。需紹介状。御茶ノ水駅步行3分。",
    "updated": "2026-04",
    "extraBadges": [
      {
        "label": "19语言通译",
        "type": "new"
      }
    ],
    "searchKeys": "東京科学大学病院 国際医療部 东京 医科歯科"
  },
  {
    "name": "東京都立駒込病院",
    "jpName": "東京都立駒込病院",
    "region": "东京",
    "address": "东京都文京区本駒込3-18-22",
    "addressShort": "东京都 文京区 本駒込（巣鴨駅 徒步5分）",
    "phone": "03-3823-2101",
    "langs": [
      "中文",
      "英文"
    ],
    "langDetail": "中文 英文 韩文",
    "depts": [
      "内科",
      "外科",
      "肿瘤科",
      "感染症",
      "儿科",
      "产科"
    ],
    "hours": "平日 8:30–（各科不同）",
    "hoursShort": "平日 8:30–（各科不同）",
    "closed": "周日・节假日",
    "note": "东京都指定外国人患者拠点医疗机构，官网有中文版，肿瘤及感染症（HIV等）专门病院，设患者支援中心对应外国人。巣鴨駅步行5分。",
    "updated": "2026-04",
    "extraBadges": [
      {
        "label": "拠点病院",
        "type": "new"
      }
    ],
    "searchKeys": "東京都立駒込病院 东京"
  },
  {
    "name": "東京大学附属病院 国際診療部",
    "jpName": "東京大学医学部附属病院",
    "region": "东京",
    "address": "东京都文京区本郷7-3-1",
    "addressShort": "东京都 文京区 本郷（本郷三丁目駅 徒步7分）",
    "phone": "03-3815-5411",
    "langs": [
      "中文",
      "英文"
    ],
    "langDetail": "中文 英文 及多语言",
    "depts": [
      "内科",
      "外科",
      "肿瘤科",
      "神经科",
      "心脏科",
      "产科",
      "健康体检"
    ],
    "hours": "平日 8:30–（各科不同）",
    "warning": "需持紹介状预约",
    "closed": "周日・节假日",
    "note": "设有国際診療部及国際検診センター（2020年设立），提供中文问诊单，为海外居住者提供全身检查套餐。需紹介状。本郷三丁目駅步行7分。",
    "updated": "2026-04",
    "extraBadges": [
      {
        "label": "国際検診",
        "type": "new"
      }
    ],
    "searchKeys": "東京大学附属病院 国際診療部 东京"
  },
  {
    "name": "东京医科大学病院 国际医疗部",
    "jpName": "東京医科大学病院 国際医療部",
    "region": "东京",
    "address": "东京都新宿区西新宿",
    "addressShort": "东京都 新宿区",
    "phone": "03-3342-XXXX",
    "langs": [
      "中文",
      "英文",
      "韩文"
    ],
    "langDetail": "中文 / 英文 / 韩文",
    "depts": [
      "内科",
      "心脏科",
      "肿瘤科",
      "妇科"
    ],
    "hours": "周一至周五 9:00–17:00",
    "hoursShort": "周一至周五 9:00–17:00",
    "closed": "周末・节假日",
    "note": "需提前通过官网预约国际医疗部，可指定中文翻译陪诊。部分科室需转诊函（紹介状）。",
    "updated": "2026-01",
    "extraBadges": [
      {
        "label": "新",
        "type": "new"
      }
    ],
    "searchKeys": "东京医科大学病院国际医疗部"
  },
  {
    "name": "Tokyo Station International Clinic",
    "jpName": "東京ステーションインターナショナルクリニック",
    "region": "东京",
    "address": "东京都千代田区 JR东京站八重洲南口步行1分钟",
    "addressShort": "东京都 千代田区（JR东京站 八重洲南口 徒步1分）",
    "phone": "官网预约",
    "langs": [
      "中文",
      "英文"
    ],
    "langDetail": "中文 英文",
    "depts": [
      "内科",
      "外科",
      "儿科",
      "皮肤科",
      "健康体检",
      "疫苗"
    ],
    "hours": "每天 9:00–21:00（365天营业）",
    "hoursShort": "每天 9:00–21:00（无休）",
    "closed": "无休",
    "note": "全员中英文对应，每月接诊700名以上外国患者，东京站八重洲南口步行1分。支持无预约当日受诊及线上预约，可出具英中文诊断证明书，支持上门往诊。",
    "updated": "2026-04",
    "extraBadges": [
      {
        "label": "365天",
        "type": "new"
      }
    ],
    "searchKeys": "Tokyo Station International Clinic 东京站国际诊所"
  },
  {
    "name": "日中友好医院",
    "jpName": "医療法人社団 日中友好医院",
    "region": "东京",
    "address": "东京都渋谷区代々木1-38-5 KDX代々木ビル6F",
    "addressShort": "东京都 渋谷区 代々木（JR代々木駅 徒步1分）",
    "phone": "03-6276-9788",
    "langs": [
      "中文",
      "英文"
    ],
    "langDetail": "中文 英文 德文",
    "depts": [
      "内科",
      "汉方",
      "健康体检",
      "疫苗"
    ],
    "hours": "周一至周五 10:00–12:30 / 14:30–16:30",
    "hoursShort": "周一至周五 10:00–12:30 / 14:30–16:30",
    "closed": "周六・周日・节假日",
    "note": "JR代々木駅前徒步1分。院长可对应中文・英文・德语，系中国大使馆指定体检机构，可办理赴华签证所需外国人体格检查记录。漢方外来也对应。",
    "updated": "2026-04",
    "extraBadges": [
      {
        "label": "中国大使馆指定",
        "type": "new"
      }
    ],
    "searchKeys": "日中友好医院 东京 代々木"
  },
  {
    "name": "宮田胃腸内科皮膚科クリニック",
    "jpName": "宮田胃腸内科皮膚科クリニック",
    "region": "东京",
    "address": "东京都新宿区百人町1-11-2 2F",
    "addressShort": "东京都 新宿区 百人町（新大久保駅 徒步3分）",
    "phone": "03-5937-0668",
    "langs": [
      "中文",
      "英文"
    ],
    "langDetail": "中文（普通话・台语）英文 韩文 泰文",
    "depts": [
      "内科",
      "皮肤科",
      "儿科",
      "汉方"
    ],
    "hours": "周一・二・四・五 9:30–12:30 / 15:00–18:30 / 周六 9:30–12:30",
    "hoursShort": "平日 9:30–12:30 / 15:00–18:30 / 周六午前",
    "closed": "周三・周日・节假日",
    "note": "院长宮田直輝毕业于台湾台北医科大学，对应中文（含台语）・英文・泰文・韩文。内镜专科，当日胃镜・大肠镜检查可对应。新大久保站徒步3分，新宿外国人聚集区。",
    "updated": "2026-04",
    "searchKeys": "宮田胃腸内科皮膚科クリニック 新大久保 东京"
  },
  {
    "name": "大阪市立住友病院",
    "jpName": "大阪市立住友病院",
    "region": "大阪",
    "addressShort": "大阪府 大阪市北区",
    "langs": [
      "中文"
    ],
    "depts": [
      "内科",
      "外科",
      "皮肤科",
      "耳鼻喉科"
    ],
    "hoursShort": "周一至周六 8:30–17:00",
    "updated": "2025-11",
    "searchKeys": "大阪市立住友病院"
  },
  {
    "name": "福冈县立病院 国际部",
    "jpName": "福岡県立病院 国際部",
    "region": "福冈",
    "addressShort": "福冈县 福冈市博多区",
    "langs": [
      "中文",
      "英文"
    ],
    "depts": [
      "内科",
      "外科",
      "儿科",
      "产科"
    ],
    "hoursShort": "周一至周五 9:00–18:00",
    "updated": "2025-10",
    "searchKeys": "福冈县立病院 国际部"
  },
  {
    "name": "札幌医科大学附属病院",
    "jpName": "札幌医科大学附属病院",
    "region": "札幌",
    "addressShort": "北海道 札幌市中央区",
    "langs": [
      "中文"
    ],
    "depts": [
      "内科",
      "外科",
      "骨科",
      "神经科"
    ],
    "hoursShort": "周一至周五 8:30–16:30",
    "updated": "2025-09",
    "searchKeys": "札幌医科大学附属病院"
  },
  {
    "name": "希咲クリニック",
    "jpName": "希咲クリニック",
    "region": "大阪",
    "address": "大阪府大阪市淀川区十三東2-7-8 エルディ十三東駅前ビル3F",
    "addressShort": "大阪府 淀川区 十三東（阪急十三駅 徒步2分）",
    "phone": "06-6476-7233",
    "langs": [
      "中文",
      "英文"
    ],
    "langDetail": "中文 英文",
    "depts": [
      "产科",
      "妇科",
      "乳腺科"
    ],
    "hours": "周一～五 9:30–12:30 / 15:00–19:00 / 周六 9:30–12:30",
    "hoursShort": "午前 9:30–12:30 / 午後 15:00–19:00",
    "closed": "周三下午・周六下午・周日・节假日",
    "note": "院长山分ネルソン祥興来自马来西亚，对应中文、英文，全科女性专科诊所。土曜日午後・水曜日は休診。",
    "updated": "2026-04",
    "searchKeys": "希咲クリニック"
  },
  {
    "name": "こどもクリニックきじま",
    "jpName": "こどもクリニックきじま",
    "region": "大阪",
    "address": "大阪府大阪市福島区福島5-6-16 ラグザ大阪サウスオフィス4F",
    "addressShort": "大阪府 福島区 福島5丁目（JR福島駅 徒步1分）",
    "phone": "06-6131-9858",
    "langs": [
      "中文"
    ],
    "langDetail": "中文",
    "depts": [
      "儿科",
      "内科",
      "过敏科"
    ],
    "hours": "周一至周日・节假日 9:00–12:00 / 16:00–20:00 (年中无休)",
    "hoursShort": "年中无休 9:00–20:00",
    "closed": "无固定休诊日（请提前确认）",
    "note": "对应中文・韩文。土日节假日也营业至20时，年中无休。非感染者专用时间段13:30–15:30。提供网络预约及线上初诊。",
    "updated": "2026-04",
    "searchKeys": "こどもクリニックきじま"
  },
  {
    "name": "春次医院",
    "jpName": "春次医院（はるつぐいいん）",
    "region": "大阪",
    "address": "大阪府大阪市中央区博労町2-6-1 心斎橋春次ビル",
    "addressShort": "大阪府 中央区 博労町（心斎橋・長堀橋 徒步7分）",
    "phone": "06-4708-3535 / 涉外担当: 080-9754-5302",
    "langs": [
      "中文"
    ],
    "langDetail": "中文",
    "depts": [
      "内科",
      "外科",
      "骨科",
      "耳鼻喉科",
      "皮肤科"
    ],
    "hours": "周一～周五 9:00–13:00 / 15:00–18:30 / 周六 9:00–13:00",
    "hoursShort": "平日 9:00–13:00 / 15:00–18:30",
    "closed": "周日・节假日",
    "note": "网站有完整中文版。涉外担当电话080-9754-5302可中文对应，微信ID: harutugu88，为中国大使馆指定PCR检查机构，支持线上问诊。",
    "updated": "2026-04",
    "extraBadges": [
      {
        "label": "中文网站",
        "type": "new"
      }
    ],
    "searchKeys": "春次医院"
  },
  {
    "name": "琥珀クリニック",
    "jpName": "琥珀クリニック",
    "region": "大阪",
    "address": "大阪府大阪市中央区南船場3-8-14 ACN心斎橋Garden4F",
    "addressShort": "大阪府 中央区 南船場（心斎橋駅 徒步3分）",
    "phone": "06-4256-4122",
    "langs": [
      "中文",
      "粤语",
      "英文"
    ],
    "langDetail": "中文 粤语 英文",
    "depts": [
      "内科",
      "汉方",
      "皮肤科"
    ],
    "hours": "周二至周六 13:00–21:00 / 周六上午 9:00–13:00",
    "hoursShort": "周二至周六 13:00–21:00",
    "closed": "周日・周一・节假日不定休（需提前电话确认）",
    "note": "院长林 宇（林宇医师）本人精通日・英・普通话・广东话・客家话，不需要翻译陪同，可直接沟通。支持线上问诊。",
    "updated": "2026-04",
    "searchKeys": "琥珀クリニック"
  },
  {
    "name": "茜道頓堀クリニック",
    "jpName": "茜道頓堀クリニック",
    "region": "大阪",
    "address": "大阪府大阪市中央区島之内2-2-2",
    "addressShort": "大阪府 中央区 島之内（日本橋駅 徒步6分）",
    "phone": "06-6213-3311",
    "langs": [
      "中文",
      "英文"
    ],
    "langDetail": "中文 英文",
    "depts": [
      "内科",
      "外科",
      "皮肤科"
    ],
    "hours": "12:00–21:00（周三・周日为特别诊疗，一般诊察需预约）",
    "hoursShort": "12:00–21:00（最終受付 20:00）",
    "closed": "不定休",
    "note": "官网有中文公告，多语言对应。午前诊察及周三・周日为特别诊疗，一般患者需提前预约，当日不受理。",
    "updated": "2026-04",
    "searchKeys": "茜道頓堀クリニック"
  },
  {
    "name": "医誠会国際総合病院",
    "jpName": "医誠会国際総合病院",
    "region": "大阪",
    "address": "大阪府大阪市北区南扇町4番14号 i-Mall内",
    "addressShort": "大阪府 北区 南扇町（扇町駅 徒步3分）",
    "phone": "0570-099-166",
    "langs": [
      "中文",
      "粤语",
      "英文"
    ],
    "langDetail": "中文（普通话・广东话）英文 韩文 及其他多语言",
    "depts": [
      "内科",
      "外科",
      "产科",
      "儿科",
      "骨科",
      "心脏科",
      "脑神经科",
      "眼科",
      "牙科",
      "急诊"
    ],
    "hours": "平日 8:00–11:30 / 13:00–16:00",
    "hoursShort": "平日 8:00–16:00 / 急诊24小时",
    "closed": "周六・周日・节假日",
    "note": "JMIP（外国人患者受入医療機関）认证医院，2023年10月开业的全新综合医院。对应普通话、广东话等22种语言，设有国际患者窗口，救急告示病院，可急诊。",
    "updated": "2026-04",
    "extraBadges": [
      {
        "label": "JMIP认证",
        "type": "new"
      }
    ],
    "searchKeys": "医誠会国際総合病院"
  },
  {
    "name": "みなと町歯科",
    "jpName": "みなと町歯科",
    "region": "大阪",
    "address": "大阪府大阪市浪速区幸町1-1-1 夕張家ビル201号",
    "addressShort": "大阪府 浪速区 幸町（JR難波駅 徒步5分）",
    "phone": "06-6567-2152",
    "langs": [
      "英文"
    ],
    "langDetail": "英文",
    "depts": [
      "牙科"
    ],
    "hours": "周一・周三・周五 10:00–13:00 / 14:00–17:00 / 周二・周四 10:00–13:00（午前のみ）/ 周日 10:00–13:00（预约制）",
    "hoursShort": "10:00–17:00（火・木 午前のみ）",
    "closed": "周六（不定）",
    "note": "提供英文对应。周日・节假日需提前预约。年末年始12/31–1/3休诊。官网有英文版，母语级别英语医生仅周日出诊。",
    "updated": "2026-04",
    "searchKeys": "みなと町歯科"
  },
  {
    "name": "Osaka Lee Clinic（イークリニック）",
    "jpName": "Osaka Lee Clinic / イークリニック",
    "region": "大阪",
    "address": "大阪府大阪市北区本庄西1-13-15",
    "addressShort": "大阪府 北区 本庄西（天満駅 徒步约10分）",
    "phone": "06-6292-0155",
    "langs": [
      "中文",
      "英文"
    ],
    "langDetail": "中文 英文 韩文",
    "depts": [
      "内科",
      "健康体检",
      "康复"
    ],
    "hours": "平日・周六 详见官网",
    "hoursShort": "详见官网 goleeclinic.com",
    "closed": "周日・节假日",
    "note": "1998年开业的社区内科诊所，提供日・英・普通话・韩文四语种服务，设有健康体检中心（2楼）及上门康复服务（3楼）。官网有中文版。",
    "updated": "2026-04",
    "searchKeys": "Osaka Lee Clinic イークリニック"
  },
  {
    "name": "大阪天満橋 Y&Y歯科・矯正歯科",
    "jpName": "大阪天満橋 Y&Y歯科・矯正歯科",
    "region": "大阪",
    "address": "大阪府大阪市中央区谷町2-2-18 2F",
    "addressShort": "大阪府 中央区 谷町2丁目（天満橋駅 徒步5分）",
    "phone": "06-6966-5548 / 中文热线: 090-6609-6686",
    "langs": [
      "中文",
      "英文"
    ],
    "langDetail": "中文 英文",
    "depts": [
      "牙科"
    ],
    "hours": "周一・二・四・五 10:00–20:00 / 周六・日 10:00–17:00",
    "hoursShort": "平日 10:00–20:00 / 土日 10:00–17:00",
    "closed": "周三・节假日",
    "note": "女性院长（大阪歯科大学大学院博士），中文对应员工常驻，有中文专线090-6609-6686及微信 yy-dental，支持支付宝・微信支付，面向短期赴日患者提供短期集中治疗套餐。",
    "updated": "2026-04",
    "extraBadges": [
      {
        "label": "微信对应",
        "type": "new"
      }
    ],
    "searchKeys": "大阪天満橋Y&Y歯科・矯正歯科"
  },
  {
    "name": "名古屋第二赤十字病院",
    "jpName": "名古屋第二赤十字病院",
    "region": "名古屋",
    "addressShort": "爱知县 名古屋市昭和区",
    "langs": [
      "中文",
      "英文"
    ],
    "depts": [
      "内科",
      "急诊",
      "妇科",
      "精神科"
    ],
    "hoursShort": "24小时急诊 / 门诊 8:30–17:00",
    "updated": "2026-01",
    "searchKeys": "名古屋第二赤十字病院"
  }
]
